{
  "id": "p2-066",
  "part": "2",
  "number": "066",
  "year": 1991,
  "rarity": "standard",
  "title_jp": "悟空大活劇!!",
  "title_en": "Goku in all-out action!!",
  "title_fr": "Goku en pleine action !!",
  "front_image_url": "https://fchavonet.github.io/full_stack-db_visual_adventure_cards_api/assets/images/front/part_2-066.png",
  "back_image_url": "https://fchavonet.github.io/full_stack-db_visual_adventure_cards_api/assets/images/back/part_2-066.png",
  "updated_at": "2025-10-25T05:18:11.466Z"
}
